{
  "attributes": [
    {
      "allow_nil?": false,
      "default": "nil",
      "generated?": false,
      "precision": null,
      "primary_key?": true,
      "references": {
        "deferrable": false,
        "destination_attribute": "id",
        "destination_attribute_default": null,
        "destination_attribute_generated": null,
        "index?": false,
        "match_type": null,
        "match_with": null,
        "multitenancy": {
          "attribute": null,
          "global": null,
          "strategy": null
        },
        "name": "ingredient_effects_ingredient_id_fkey",
        "on_delete": null,
        "on_update": null,
        "primary_key?": true,
        "schema": "public",
        "table": "ingredients"
      },
      "scale": null,
      "size": null,
      "source": "ingredient_id",
      "type": "text"
    },
    {
      "allow_nil?": false,
      "default": "nil",
      "generated?": false,
      "precision": null,
      "primary_key?": true,
      "references": {
        "deferrable": false,
        "destination_attribute": "id",
        "destination_attribute_default": null,
        "destination_attribute_generated": null,
        "index?": false,
        "match_type": null,
        "match_with": null,
        "multitenancy": {
          "attribute": null,
          "global": null,
          "strategy": null
        },
        "name": "ingredient_effects_magic_effect_id_fkey",
        "on_delete": null,
        "on_update": null,
        "primary_key?": true,
        "schema": "public",
        "table": "magic_effects"
      },
      "scale": null,
      "size": null,
      "source": "magic_effect_id",
      "type": "text"
    }
  ],
  "base_filter": null,
  "check_constraints": [],
  "custom_indexes": [],
  "custom_statements": [],
  "has_create_action": false,
  "hash": "B2A7BD196B9A7C21B589333B932B0717359DAA6615AEFA082D32936EE9F336C0",
  "identities": [],
  "multitenancy": {
    "attribute": null,
    "global": null,
    "strategy": null
  },
  "repo": "Elixir.Resdayn.Repo",
  "schema": null,
  "table": "ingredient_effects"
}